topsis/__init__.py
topsis/__main__.py
topsis_Suhawni_102103344-1.0.2.dist-info/LICENSE
topsis_Suhawni_102103344-1.0.2.dist-info/METADATA
topsis_Suhawni_102103344-1.0.2.dist-info/WHEEL
topsis_Suhawni_102103344-1.0.2.dist-info/entry_points.txt
topsis_Suhawni_102103344-1.0.2.dist-info/top_level.txt
topsis_Suhawni_102103344-1.0.2.dist-info/RECORD
